jupyter_output_monitor/__init__.py
jupyter_output_monitor/__main__.py
jupyter_output_monitor/_convert.py
jupyter_output_monitor/_monitor.py
jupyter_output_monitor/_report.py
jupyter_output_monitor/_server.py
jupyter_output_monitor/_utils.py
jupyter_output_monitor/_version.py
jupyter_output_monitor/tests/__init__.py
jupyter_output_monitor/tests/test_monitor.py
jupyter_output_monitor/tests/data/simple.ipynb
jupyter_output_monitor-0.1.0a1.dist-info/LICENSE
jupyter_output_monitor-0.1.0a1.dist-info/METADATA
jupyter_output_monitor-0.1.0a1.dist-info/WHEEL
jupyter_output_monitor-0.1.0a1.dist-info/entry_points.txt
jupyter_output_monitor-0.1.0a1.dist-info/top_level.txt
jupyter_output_monitor-0.1.0a1.dist-info/RECORD
