Metadata-Version: 2.2
Name: jupyter-output-monitor
Version: 0.1.0a1
Summary: Monitor the visual output of Jupyter notebook cells
Author-email: Thomas Robitaille <thomas.robitaille@gmail.com>
License: BSD 3-Clause
Project-URL: Homepage, https://github.com/glue-viz/jupyter-output-monitor
Requires-Python: >=3.10
License-File: LICENSE
Requires-Dist: numpy>=1.23
Requires-Dist: click
Requires-Dist: pillow
Requires-Dist: playwright
Requires-Dist: solara[pytest]
Requires-Dist: nbformat
Provides-Extra: test
Requires-Dist: pytest>=7.0; extra == "test"
Requires-Dist: ipywidgets; extra == "test"
